{"tableData": [{"isPremium": false, "problemName": "1451. Rearrange Words in a Sentence", "haveSolution": false, "isVideoSolution": false, "acceptance": "63.0%", "difficulty": "Medium", "frequency": "34.2395%", "url": "https://leetcode.com/problems/rearrange-words-in-a-sentence/"}, {"isPremium": false, "problemName": "1452. People Whose List of Favorite Companies Is Not a Subset of Another List", "haveSolution": false, "isVideoSolution": false, "acceptance": "56.8%", "difficulty": "Medium", "frequency": "13.0471%", "url": "https://leetcode.com/problems/people-whose-list-of-favorite-companies-is-not-a-subset-of-another-list/"}, {"isPremium": false, "problemName": "1453. Maximum Number of Darts Inside of a Circular Dartboard", "haveSolution": false, "isVideoSolution": false, "acceptance": "36.9%", "difficulty": "Hard", "frequency": "28.6221%", "url": "https://leetcode.com/problems/maximum-number-of-darts-inside-of-a-circular-dartboard/"}, {"isPremium": false, "problemName": "1454. Active Users", "haveSolution": false, "isVideoSolution": false, "acceptance": "38.0%", "difficulty": "Medium", "frequency": "24.5315%", "url": "https://leetcode.com/problems/active-users/"}, {"isPremium": false, "problemName": "1455. Check If a Word Occurs As a Prefix of Any Word in a Sentence", "haveSolution": false, "isVideoSolution": false, "acceptance": "64.3%", "difficulty": "Easy", "frequency": "3.42222%", "url": "https://leetcode.com/problems/check-if-a-word-occurs-as-a-prefix-of-any-word-in-a-sentence/"}, {"isPremium": false, "problemName": "1456. Maximum Number of Vowels in a Substring of Given Length", "haveSolution": false, "isVideoSolution": false, "acceptance": "58.2%", "difficulty": "Medium", "frequency": "16.2356%", "url": "https://leetcode.com/problems/maximum-number-of-vowels-in-a-substring-of-given-length/"}, {"isPremium": false, "problemName": "1457. Pseudo-Palindromic Paths in a Binary Tree", "haveSolution": true, "isVideoSolution": false, "acceptance": "67.9%", "difficulty": "Medium", "frequency": "56.5127%", "url": "https://leetcode.com/problems/pseudo-palindromic-paths-in-a-binary-tree/"}, {"isPremium": false, "problemName": "1458. Max Dot Product of Two Subsequences", "haveSolution": false, "isVideoSolution": false, "acceptance": "46.6%", "difficulty": "Hard", "frequency": "36.0557%", "url": "https://leetcode.com/problems/max-dot-product-of-two-subsequences/"}, {"isPremium": false, "problemName": "1459. Rectangles Area", "haveSolution": false, "isVideoSolution": false, "acceptance": "69.9%", "difficulty": "Medium", "frequency": "10.5117%", "url": "https://leetcode.com/problems/rectangles-area/"}, {"isPremium": false, "problemName": "1460. Make Two Arrays Equal by Reversing Subarrays", "haveSolution": false, "isVideoSolution": false, "acceptance": "72.2%", "difficulty": "Easy", "frequency": "10.9505%", "url": "https://leetcode.com/problems/make-two-arrays-equal-by-reversing-subarrays/"}, {"isPremium": false, "problemName": "1461. Check If a String Contains All Binary Codes of Size K", "haveSolution": true, "isVideoSolution": false, "acceptance": "56.6%", "difficulty": "Medium", "frequency": "5.6921%", "url": "https://leetcode.com/problems/check-if-a-string-contains-all-binary-codes-of-size-k/"}, {"isPremium": false, "problemName": "1462. Course Schedule IV", "haveSolution": false, "isVideoSolution": false, "acceptance": "49.0%", "difficulty": "Medium", "frequency": "9.71314%", "url": "https://leetcode.com/problems/course-schedule-iv/"}, {"isPremium": false, "problemName": "1463. Cherry Pickup II", "haveSolution": true, "isVideoSolution": false, "acceptance": "69.9%", "difficulty": "Hard", "frequency": "38.4199%", "url": "https://leetcode.com/problems/cherry-pickup-ii/"}, {"isPremium": false, "problemName": "1464. Maximum Product of Two Elements in an Array", "haveSolution": false, "isVideoSolution": false, "acceptance": "79.7%", "difficulty": "Easy", "frequency": "30.3927%", "url": "https://leetcode.com/problems/maximum-product-of-two-elements-in-an-array/"}, {"isPremium": false, "problemName": "1465. Maximum Area of a Piece of Cake After Horizontal and Vertical Cuts", "haveSolution": true, "isVideoSolution": false, "acceptance": "40.9%", "difficulty": "Medium", "frequency": "61.0574%", "url": "https://leetcode.com/problems/maximum-area-of-a-piece-of-cake-after-horizontal-and-vertical-cuts/"}, {"isPremium": false, "problemName": "1466. Reorder Routes to Make All Paths Lead to the City Zero", "haveSolution": false, "isVideoSolution": false, "acceptance": "61.7%", "difficulty": "Medium", "frequency": "38.3508%", "url": "https://leetcode.com/problems/reorder-routes-to-make-all-paths-lead-to-the-city-zero/"}, {"isPremium": false, "problemName": "1467. Probability of a Two Boxes Having The Same Number of Distinct Balls", "haveSolution": false, "isVideoSolution": false, "acceptance": "60.9%", "difficulty": "Hard", "frequency": "0%", "url": "https://leetcode.com/problems/probability-of-a-two-boxes-having-the-same-number-of-distinct-balls/"}, {"isPremium": false, "problemName": "1468. Calculate Salaries", "haveSolution": false, "isVideoSolution": false, "acceptance": "81.3%", "difficulty": "Medium", "frequency": "0%", "url": "https://leetcode.com/problems/calculate-salaries/"}, {"isPremium": false, "problemName": "1469. Find All The Lonely Nodes", "haveSolution": false, "isVideoSolution": false, "acceptance": "82.0%", "difficulty": "Easy", "frequency": "0%", "url": "https://leetcode.com/problems/find-all-the-lonely-nodes/"}, {"isPremium": false, "problemName": "1470. Shuffle the Array", "haveSolution": true, "isVideoSolution": false, "acceptance": "88.4%", "difficulty": "Easy", "frequency": "55.6192%", "url": "https://leetcode.com/problems/shuffle-the-array/"}, {"isPremium": false, "problemName": "1471. The k Strongest Values in an Array", "haveSolution": false, "isVideoSolution": false, "acceptance": "60.3%", "difficulty": "Medium", "frequency": "0%", "url": "https://leetcode.com/problems/the-k-strongest-values-in-an-array/"}, {"isPremium": false, "problemName": "1472. Design Browser History", "haveSolution": true, "isVideoSolution": false, "acceptance": "76.2%", "difficulty": "Medium", "frequency": "74.6185%", "url": "https://leetcode.com/problems/design-browser-history/"}, {"isPremium": false, "problemName": "1473. Paint House III", "haveSolution": true, "isVideoSolution": false, "acceptance": "61.8%", "difficulty": "Hard", "frequency": "40.7286%", "url": "https://leetcode.com/problems/paint-house-iii/"}, {"isPremium": false, "problemName": "1474. Delete N Nodes After M Nodes of a Linked List", "haveSolution": true, "isVideoSolution": false, "acceptance": "73.6%", "difficulty": "Easy", "frequency": "0%", "url": "https://leetcode.com/problems/delete-n-nodes-after-m-nodes-of-a-linked-list/"}, {"isPremium": false, "problemName": "1475. Final Prices With a Special Discount in a Shop", "haveSolution": false, "isVideoSolution": false, "acceptance": "75.8%", "difficulty": "Easy", "frequency": "25.5693%", "url": "https://leetcode.com/problems/final-prices-with-a-special-discount-in-a-shop/"}, {"isPremium": false, "problemName": "1476. Subrectangle Queries", "haveSolution": false, "isVideoSolution": false, "acceptance": "88.4%", "difficulty": "Medium", "frequency": "22.2821%", "url": "https://leetcode.com/problems/subrectangle-queries/"}, {"isPremium": false, "problemName": "1477. Find Two Non-overlapping Sub-arrays Each With Target Sum", "haveSolution": false, "isVideoSolution": false, "acceptance": "36.8%", "difficulty": "Medium", "frequency": "21.9078%", "url": "https://leetcode.com/problems/find-two-non-overlapping-sub-arrays-each-with-target-sum/"}, {"isPremium": false, "problemName": "1478. Allocate Mailboxes", "haveSolution": false, "isVideoSolution": false, "acceptance": "55.6%", "difficulty": "Hard", "frequency": "48.2913%", "url": "https://leetcode.com/problems/allocate-mailboxes/"}, {"isPremium": false, "problemName": "1479. Sales by Day of the Week", "haveSolution": false, "isVideoSolution": false, "acceptance": "81.6%", "difficulty": "Hard", "frequency": "16.8712%", "url": "https://leetcode.com/problems/sales-by-day-of-the-week/"}, {"isPremium": false, "problemName": "1480. Running Sum of 1d Array", "haveSolution": true, "isVideoSolution": true, "acceptance": "88.2%", "difficulty": "Easy", "frequency": "86.5034%", "url": "https://leetcode.com/problems/running-sum-of-1d-array/"}, {"isPremium": false, "problemName": "1481. Least Number of Unique Integers after K Removals", "haveSolution": false, "isVideoSolution": false, "acceptance": "56.2%", "difficulty": "Medium", "frequency": "66.3189%", "url": "https://leetcode.com/problems/least-number-of-unique-integers-after-k-removals/"}, {"isPremium": false, "problemName": "1482. Minimum Number of Days to Make m Bouquets", "haveSolution": false, "isVideoSolution": false, "acceptance": "54.6%", "difficulty": "Medium", "frequency": "50.1361%", "url": "https://leetcode.com/problems/minimum-number-of-days-to-make-m-bouquets/"}, {"isPremium": false, "problemName": "1483. Kth Ancestor of a Tree Node", "haveSolution": false, "isVideoSolution": false, "acceptance": "33.7%", "difficulty": "Hard", "frequency": "40.6321%", "url": "https://leetcode.com/problems/kth-ancestor-of-a-tree-node/"}, {"isPremium": false, "problemName": "1484. Group Sold Products By The Date", "haveSolution": false, "isVideoSolution": false, "acceptance": "81.2%", "difficulty": "Easy", "frequency": "30.609%", "url": "https://leetcode.com/problems/group-sold-products-by-the-date/"}, {"isPremium": false, "problemName": "1485. Clone Binary Tree With Random Pointer", "haveSolution": true, "isVideoSolution": false, "acceptance": "79.3%", "difficulty": "Medium", "frequency": "19.0565%", "url": "https://leetcode.com/problems/clone-binary-tree-with-random-pointer/"}, {"isPremium": false, "problemName": "1486. XOR Operation in an Array", "haveSolution": false, "isVideoSolution": false, "acceptance": "84.5%", "difficulty": "Easy", "frequency": "23.2493%", "url": "https://leetcode.com/problems/xor-operation-in-an-array/"}, {"isPremium": false, "problemName": "1487. Making File Names Unique", "haveSolution": false, "isVideoSolution": false, "acceptance": "36.1%", "difficulty": "Medium", "frequency": "50.5122%", "url": "https://leetcode.com/problems/making-file-names-unique/"}, {"isPremium": false, "problemName": "1488. Avoid Flood in The City", "haveSolution": false, "isVideoSolution": false, "acceptance": "26.3%", "difficulty": "Medium", "frequency": "53.5147%", "url": "https://leetcode.com/problems/avoid-flood-in-the-city/"}, {"isPremium": false, "problemName": "1489. Find Critical and Pseudo-Critical Edges in Minimum Spanning Tree", "haveSolution": false, "isVideoSolution": false, "acceptance": "52.8%", "difficulty": "Hard", "frequency": "25.1153%", "url": "https://leetcode.com/problems/find-critical-and-pseudo-critical-edges-in-minimum-spanning-tree/"}, {"isPremium": false, "problemName": "1490. Clone N-ary Tree", "haveSolution": true, "isVideoSolution": false, "acceptance": "83.5%", "difficulty": "Medium", "frequency": "0%", "url": "https://leetcode.com/problems/clone-n-ary-tree/"}, {"isPremium": false, "problemName": "1491. Average Salary Excluding the Minimum and Maximum Salary", "haveSolution": false, "isVideoSolution": false, "acceptance": "61.9%", "difficulty": "Easy", "frequency": "39.5469%", "url": "https://leetcode.com/problems/average-salary-excluding-the-minimum-and-maximum-salary/"}, {"isPremium": false, "problemName": "1492. The kth Factor of n", "haveSolution": true, "isVideoSolution": false, "acceptance": "62.6%", "difficulty": "Medium", "frequency": "26.3462%", "url": "https://leetcode.com/problems/the-kth-factor-of-n/"}, {"isPremium": false, "problemName": "1493. Longest Subarray of 1's After Deleting One Element", "haveSolution": false, "isVideoSolution": false, "acceptance": "60.4%", "difficulty": "Medium", "frequency": "59.5132%", "url": "https://leetcode.com/problems/longest-subarray-of-1s-after-deleting-one-element/"}, {"isPremium": false, "problemName": "1494. Parallel Courses II", "haveSolution": false, "isVideoSolution": false, "acceptance": "30.6%", "difficulty": "Hard", "frequency": "46.1533%", "url": "https://leetcode.com/problems/parallel-courses-ii/"}, {"isPremium": false, "problemName": "1495. Friendly Movies Streamed Last Month", "haveSolution": false, "isVideoSolution": false, "acceptance": "49.4%", "difficulty": "Easy", "frequency": "0%", "url": "https://leetcode.com/problems/friendly-movies-streamed-last-month/"}, {"isPremium": false, "problemName": "1496. Path Crossing", "haveSolution": false, "isVideoSolution": false, "acceptance": "55.9%", "difficulty": "Easy", "frequency": "26.73%", "url": "https://leetcode.com/problems/path-crossing/"}, {"isPremium": false, "problemName": "1497. Check If Array Pairs Are Divisible by k", "haveSolution": false, "isVideoSolution": false, "acceptance": "39.3%", "difficulty": "Medium", "frequency": "50.2153%", "url": "https://leetcode.com/problems/check-if-array-pairs-are-divisible-by-k/"}, {"isPremium": false, "problemName": "1498. Number of Subsequences That Satisfy the Given Sum Condition", "haveSolution": false, "isVideoSolution": false, "acceptance": "37.6%", "difficulty": "Medium", "frequency": "43.0791%", "url": "https://leetcode.com/problems/number-of-subsequences-that-satisfy-the-given-sum-condition/"}, {"isPremium": false, "problemName": "1499. Max Value of Equation", "haveSolution": false, "isVideoSolution": false, "acceptance": "46.0%", "difficulty": "Hard", "frequency": "54.6357%", "url": "https://leetcode.com/problems/max-value-of-equation/"}, {"isPremium": false, "problemName": "1500. Design a File Sharing System", "haveSolution": false, "isVideoSolution": false, "acceptance": "44.8%", "difficulty": "Medium", "frequency": "46.5167%", "url": "https://leetcode.com/problems/design-a-file-sharing-system/"}], "page": "30"}