{"tableData": [{"isPremium": false, "problemName": "2201. Count Artifacts That Can Be Extracted", "haveSolution": false, "isVideoSolution": false, "acceptance": "55.3%", "difficulty": "Medium", "frequency": "21.9078%", "url": "https://leetcode.com/problems/count-artifacts-that-can-be-extracted/"}, {"isPremium": false, "problemName": "2202. Maximize the Topmost Element After K Moves", "haveSolution": false, "isVideoSolution": false, "acceptance": "22.8%", "difficulty": "Medium", "frequency": "20.378%", "url": "https://leetcode.com/problems/maximize-the-topmost-element-after-k-moves/"}, {"isPremium": false, "problemName": "2203. Minimum Weighted Subgraph With the Required Paths", "haveSolution": false, "isVideoSolution": false, "acceptance": "36.0%", "difficulty": "Hard", "frequency": "42.7141%", "url": "https://leetcode.com/problems/minimum-weighted-subgraph-with-the-required-paths/"}, {"isPremium": false, "problemName": "2204. Distance to a Cycle in Undirected Graph", "haveSolution": false, "isVideoSolution": false, "acceptance": "70.2%", "difficulty": "Hard", "frequency": "0%", "url": "https://leetcode.com/problems/distance-to-a-cycle-in-undirected-graph/"}, {"isPremium": false, "problemName": "2205. The Number of Users That Are Eligible for Discount", "haveSolution": false, "isVideoSolution": false, "acceptance": "50.8%", "difficulty": "Easy", "frequency": "0%", "url": "https://leetcode.com/problems/the-number-of-users-that-are-eligible-for-discount/"}, {"isPremium": false, "problemName": "2206. Divide Array Into Equal Pairs", "haveSolution": false, "isVideoSolution": false, "acceptance": "74.3%", "difficulty": "Easy", "frequency": "21.8741%", "url": "https://leetcode.com/problems/divide-array-into-equal-pairs/"}, {"isPremium": false, "problemName": "2207. Maximize Number of Subsequences in a String", "haveSolution": false, "isVideoSolution": false, "acceptance": "33.2%", "difficulty": "Medium", "frequency": "28.6221%", "url": "https://leetcode.com/problems/maximize-number-of-subsequences-in-a-string/"}, {"isPremium": false, "problemName": "2208. Minimum Operations to Halve Array Sum", "haveSolution": false, "isVideoSolution": false, "acceptance": "45.3%", "difficulty": "Medium", "frequency": "30.2828%", "url": "https://leetcode.com/problems/minimum-operations-to-halve-array-sum/"}, {"isPremium": false, "problemName": "2209. Minimum White Tiles After Covering With Carpets", "haveSolution": false, "isVideoSolution": false, "acceptance": "34.0%", "difficulty": "Hard", "frequency": "71.1602%", "url": "https://leetcode.com/problems/minimum-white-tiles-after-covering-with-carpets/"}, {"isPremium": false, "problemName": "2210. Count Hills and Valleys in an Array", "haveSolution": false, "isVideoSolution": false, "acceptance": "58.4%", "difficulty": "Easy", "frequency": "47.9467%", "url": "https://leetcode.com/problems/count-hills-and-valleys-in-an-array/"}, {"isPremium": false, "problemName": "2211. Count Collisions on a Road", "haveSolution": false, "isVideoSolution": false, "acceptance": "42.2%", "difficulty": "Medium", "frequency": "0%", "url": "https://leetcode.com/problems/count-collisions-on-a-road/"}, {"isPremium": false, "problemName": "2212. Maximum Points in an Archery Competition", "haveSolution": false, "isVideoSolution": false, "acceptance": "49.4%", "difficulty": "Medium", "frequency": "46.7904%", "url": "https://leetcode.com/problems/maximum-points-in-an-archery-competition/"}, {"isPremium": false, "problemName": "2213. Longest Substring of One Repeating Character", "haveSolution": false, "isVideoSolution": false, "acceptance": "31.1%", "difficulty": "Hard", "frequency": "0%", "url": "https://leetcode.com/problems/longest-substring-of-one-repeating-character/"}, {"isPremium": false, "problemName": "2214. Minimum Health to Beat Game", "haveSolution": true, "isVideoSolution": false, "acceptance": "58.0%", "difficulty": "Medium", "frequency": "79.8209%", "url": "https://leetcode.com/problems/minimum-health-to-beat-game/"}, {"isPremium": false, "problemName": "2215. Find the Difference of Two Arrays", "haveSolution": false, "isVideoSolution": false, "acceptance": "70.3%", "difficulty": "Easy", "frequency": "34.8307%", "url": "https://leetcode.com/problems/find-the-difference-of-two-arrays/"}, {"isPremium": false, "problemName": "2216. Minimum Deletions to Make Array Beautiful", "haveSolution": false, "isVideoSolution": false, "acceptance": "46.8%", "difficulty": "Medium", "frequency": "29.1278%", "url": "https://leetcode.com/problems/minimum-deletions-to-make-array-beautiful/"}, {"isPremium": false, "problemName": "2217. Find Palindrome With Fixed Length", "haveSolution": false, "isVideoSolution": false, "acceptance": "34.1%", "difficulty": "Medium", "frequency": "38.9467%", "url": "https://leetcode.com/problems/find-palindrome-with-fixed-length/"}, {"isPremium": false, "problemName": "2218. Maximum Value of K Coins From Piles", "haveSolution": false, "isVideoSolution": false, "acceptance": "48.0%", "difficulty": "Hard", "frequency": "22.4746%", "url": "https://leetcode.com/problems/maximum-value-of-k-coins-from-piles/"}, {"isPremium": false, "problemName": "2219. Maximum Sum Score of Array", "haveSolution": false, "isVideoSolution": false, "acceptance": "60.2%", "difficulty": "Medium", "frequency": "25.8928%", "url": "https://leetcode.com/problems/maximum-sum-score-of-array/"}, {"isPremium": false, "problemName": "2220. Minimum Bit Flips to Convert Number", "haveSolution": false, "isVideoSolution": false, "acceptance": "82.3%", "difficulty": "Easy", "frequency": "23.4733%", "url": "https://leetcode.com/problems/minimum-bit-flips-to-convert-number/"}, {"isPremium": false, "problemName": "2221. Find Triangular Sum of an Array", "haveSolution": false, "isVideoSolution": false, "acceptance": "78.6%", "difficulty": "Medium", "frequency": "54.4179%", "url": "https://leetcode.com/problems/find-triangular-sum-of-an-array/"}, {"isPremium": false, "problemName": "2222. Number of Ways to Select Buildings", "haveSolution": false, "isVideoSolution": false, "acceptance": "51.4%", "difficulty": "Medium", "frequency": "69.9014%", "url": "https://leetcode.com/problems/number-of-ways-to-select-buildings/"}, {"isPremium": false, "problemName": "2223. Sum of Scores of Built Strings", "haveSolution": false, "isVideoSolution": false, "acceptance": "37.3%", "difficulty": "Hard", "frequency": "0%", "url": "https://leetcode.com/problems/sum-of-scores-of-built-strings/"}, {"isPremium": false, "problemName": "2224. Minimum Number of Operations to Convert Time", "haveSolution": false, "isVideoSolution": false, "acceptance": "65.5%", "difficulty": "Easy", "frequency": "0%", "url": "https://leetcode.com/problems/minimum-number-of-operations-to-convert-time/"}, {"isPremium": false, "problemName": "2225. Find Players With Zero or One Losses", "haveSolution": true, "isVideoSolution": false, "acceptance": "73.0%", "difficulty": "Medium", "frequency": "55.666%", "url": "https://leetcode.com/problems/find-players-with-zero-or-one-losses/"}, {"isPremium": false, "problemName": "2226. Maximum Candies Allocated to K Children", "haveSolution": false, "isVideoSolution": false, "acceptance": "36.4%", "difficulty": "Medium", "frequency": "13.3218%", "url": "https://leetcode.com/problems/maximum-candies-allocated-to-k-children/"}, {"isPremium": false, "problemName": "2227. Encrypt and Decrypt Strings", "haveSolution": false, "isVideoSolution": false, "acceptance": "39.4%", "difficulty": "Hard", "frequency": "51.9204%", "url": "https://leetcode.com/problems/encrypt-and-decrypt-strings/"}, {"isPremium": false, "problemName": "2228. Users With Two Purchases Within Seven Days", "haveSolution": false, "isVideoSolution": false, "acceptance": "44.3%", "difficulty": "Medium", "frequency": "0%", "url": "https://leetcode.com/problems/users-with-two-purchases-within-seven-days/"}, {"isPremium": false, "problemName": "2229. Check if an Array Is Consecutive", "haveSolution": false, "isVideoSolution": false, "acceptance": "61.3%", "difficulty": "Easy", "frequency": "0%", "url": "https://leetcode.com/problems/check-if-an-array-is-consecutive/"}, {"isPremium": false, "problemName": "2230. The Users That Are Eligible for Discount", "haveSolution": false, "isVideoSolution": false, "acceptance": "50.3%", "difficulty": "Easy", "frequency": "0%", "url": "https://leetcode.com/problems/the-users-that-are-eligible-for-discount/"}, {"isPremium": false, "problemName": "2231. Largest Number After Digit Swaps by Parity", "haveSolution": false, "isVideoSolution": false, "acceptance": "60.8%", "difficulty": "Easy", "frequency": "38.2435%", "url": "https://leetcode.com/problems/largest-number-after-digit-swaps-by-parity/"}, {"isPremium": false, "problemName": "2232. Minimize Result by Adding Parentheses to Expression", "haveSolution": false, "isVideoSolution": false, "acceptance": "65.6%", "difficulty": "Medium", "frequency": "72.5837%", "url": "https://leetcode.com/problems/minimize-result-by-adding-parentheses-to-expression/"}, {"isPremium": false, "problemName": "2233. Maximum Product After K Increments", "haveSolution": false, "isVideoSolution": false, "acceptance": "41.2%", "difficulty": "Medium", "frequency": "0%", "url": "https://leetcode.com/problems/maximum-product-after-k-increments/"}, {"isPremium": false, "problemName": "2234. Maximum Total Beauty of the Gardens", "haveSolution": false, "isVideoSolution": false, "acceptance": "28.4%", "difficulty": "Hard", "frequency": "52.4667%", "url": "https://leetcode.com/problems/maximum-total-beauty-of-the-gardens/"}, {"isPremium": false, "problemName": "2235. Add Two Integers", "haveSolution": false, "isVideoSolution": false, "acceptance": "89.0%", "difficulty": "Easy", "frequency": "82.8084%", "url": "https://leetcode.com/problems/add-two-integers/"}, {"isPremium": false, "problemName": "2236. Root Equals Sum of Children", "haveSolution": false, "isVideoSolution": false, "acceptance": "85.8%", "difficulty": "Easy", "frequency": "45.1573%", "url": "https://leetcode.com/problems/root-equals-sum-of-children/"}, {"isPremium": false, "problemName": "2237. Count Positions on Street With Required Brightness", "haveSolution": false, "isVideoSolution": false, "acceptance": "66.1%", "difficulty": "Medium", "frequency": "37.4169%", "url": "https://leetcode.com/problems/count-positions-on-street-with-required-brightness/"}, {"isPremium": false, "problemName": "2238. Number of Times a Driver Was a Passenger", "haveSolution": false, "isVideoSolution": false, "acceptance": "74.8%", "difficulty": "Medium", "frequency": "0%", "url": "https://leetcode.com/problems/number-of-times-a-driver-was-a-passenger/"}, {"isPremium": false, "problemName": "2239. Find Closest Number to Zero", "haveSolution": false, "isVideoSolution": false, "acceptance": "45.7%", "difficulty": "Easy", "frequency": "38.6235%", "url": "https://leetcode.com/problems/find-closest-number-to-zero/"}, {"isPremium": false, "problemName": "2240. Number of Ways to Buy Pens and Pencils", "haveSolution": false, "isVideoSolution": false, "acceptance": "57.1%", "difficulty": "Medium", "frequency": "13.0471%", "url": "https://leetcode.com/problems/number-of-ways-to-buy-pens-and-pencils/"}, {"isPremium": false, "problemName": "2241. Design an ATM Machine", "haveSolution": false, "isVideoSolution": false, "acceptance": "38.8%", "difficulty": "Medium", "frequency": "15.1223%", "url": "https://leetcode.com/problems/design-an-atm-machine/"}, {"isPremium": false, "problemName": "2242. Maximum Score of a Node Sequence", "haveSolution": false, "isVideoSolution": false, "acceptance": "37.8%", "difficulty": "Hard", "frequency": "58.5067%", "url": "https://leetcode.com/problems/maximum-score-of-a-node-sequence/"}, {"isPremium": false, "problemName": "2243. Calculate Digit Sum of a String", "haveSolution": false, "isVideoSolution": false, "acceptance": "66.6%", "difficulty": "Easy", "frequency": "36.6328%", "url": "https://leetcode.com/problems/calculate-digit-sum-of-a-string/"}, {"isPremium": false, "problemName": "2244. Minimum Rounds to Complete All Tasks", "haveSolution": true, "isVideoSolution": false, "acceptance": "63.0%", "difficulty": "Medium", "frequency": "85.1604%", "url": "https://leetcode.com/problems/minimum-rounds-to-complete-all-tasks/"}, {"isPremium": false, "problemName": "2245. Maximum Trailing Zeros in a Cornered Path", "haveSolution": false, "isVideoSolution": false, "acceptance": "35.0%", "difficulty": "Medium", "frequency": "37.4169%", "url": "https://leetcode.com/problems/maximum-trailing-zeros-in-a-cornered-path/"}, {"isPremium": false, "problemName": "2246. Longest Path With Different Adjacent Characters", "haveSolution": true, "isVideoSolution": false, "acceptance": "56.0%", "difficulty": "Hard", "frequency": "66.5473%", "url": "https://leetcode.com/problems/longest-path-with-different-adjacent-characters/"}, {"isPremium": false, "problemName": "2247. Maximum Cost of Trip With K Highways", "haveSolution": false, "isVideoSolution": false, "acceptance": "49.5%", "difficulty": "Hard", "frequency": "37.4169%", "url": "https://leetcode.com/problems/maximum-cost-of-trip-with-k-highways/"}, {"isPremium": false, "problemName": "2248. Intersection of Multiple Arrays", "haveSolution": false, "isVideoSolution": false, "acceptance": "69.1%", "difficulty": "Easy", "frequency": "33.7183%", "url": "https://leetcode.com/problems/intersection-of-multiple-arrays/"}, {"isPremium": false, "problemName": "2249. Count Lattice Points Inside a Circle", "haveSolution": false, "isVideoSolution": false, "acceptance": "50.4%", "difficulty": "Medium", "frequency": "0%", "url": "https://leetcode.com/problems/count-lattice-points-inside-a-circle/"}, {"isPremium": false, "problemName": "2250. Count Number of Rectangles Containing Each Point", "haveSolution": false, "isVideoSolution": false, "acceptance": "34.1%", "difficulty": "Medium", "frequency": "11.4195%", "url": "https://leetcode.com/problems/count-number-of-rectangles-containing-each-point/"}], "page": "45"}