{"tags": [{"duration": "6 months - 1 year", "companies": [["6 months - 1 year", "Google\n2"]]}, {"duration": "1 year - 2 years", "companies": [["1 year - 2 years", "Bloomberg\n2"], ["1 year - 2 years", "Turvo"]]}], "problem": "<p>Given an array of integers <code>arr</code>, and three integers&nbsp;<code>a</code>,&nbsp;<code>b</code>&nbsp;and&nbsp;<code>c</code>. You need to find the number of good triplets.</p>\n\n<p>A triplet <code>(arr[i], arr[j], arr[k])</code>&nbsp;is <strong>good</strong> if the following conditions are true:</p>\n\n<ul>\n\t<li><code>0 &lt;= i &lt; j &lt; k &lt;&nbsp;arr.length</code></li>\n\t<li><code>|arr[i] - arr[j]| &lt;= a</code></li>\n\t<li><code>|arr[j] - arr[k]| &lt;= b</code></li>\n\t<li><code>|arr[i] - arr[k]| &lt;= c</code></li>\n</ul>\n\n<p>Where <code>|x|</code> denotes the absolute value of <code>x</code>.</p>\n\n<p>Return<em> the number of good triplets</em>.</p>\n\n<p>&nbsp;</p>\n<p><strong class=\"example\">Example 1:</strong></p>\n\n<pre><strong>Input:</strong> arr = [3,0,1,1,9,7], a = 7, b = 2, c = 3\n<strong>Output:</strong> 4\n<strong>Explanation:</strong>&nbsp;There are 4 good triplets: [(3,0,1), (3,0,1), (3,1,1), (0,1,1)].\n</pre>\n\n<p><strong class=\"example\">Example 2:</strong></p>\n\n<pre><strong>Input:</strong> arr = [1,1,2,2,3], a = 0, b = 0, c = 1\n<strong>Output:</strong> 0\n<strong>Explanation: </strong>No triplet satisfies all conditions.\n</pre>\n\n<p>&nbsp;</p>\n<p><strong>Constraints:</strong></p>\n\n<ul>\n\t<li><code>3 &lt;= arr.length &lt;= 100</code></li>\n\t<li><code>0 &lt;= arr[i] &lt;= 1000</code></li>\n\t<li><code>0 &lt;= a, b, c &lt;= 1000</code></li>\n</ul>", "relatedTopics": ["Array", "Enumeration"], "similarQuestions": [{"questionName": "Count Special Quadruplets", "difficulty": "Easy"}, {"questionName": "Number of Unequal Triplets in Array", "difficulty": "Easy"}], "problemName": "count-good-triplets"}