{"tags": [{"duration": "6 months - 1 year", "companies": [["6 months - 1 year", "Epam Systems\n3"]]}, {"duration": "1 year - 2 years", "companies": [["1 year - 2 years", "Amazon\n2"], ["1 year - 2 years", "National Instruments"]]}], "problem": "<p>You are given an encoded string <code>s</code>. To decode the string to a tape, the encoded string is read one character at a time and the following steps are taken:</p>\n\n<ul>\n\t<li>If the character read is a letter, that letter is written onto the tape.</li>\n\t<li>If the character read is a digit <code>d</code>, the entire current tape is repeatedly written <code>d - 1</code> more times in total.</li>\n</ul>\n\n<p>Given an integer <code>k</code>, return <em>the </em><code>k<sup>th</sup></code><em> letter (<strong>1-indexed)</strong> in the decoded string</em>.</p>\n\n<p>&nbsp;</p>\n<p><strong class=\"example\">Example 1:</strong></p>\n\n<pre><strong>Input:</strong> s = \"leet2code3\", k = 10\n<strong>Output:</strong> \"o\"\n<strong>Explanation:</strong> The decoded string is \"leetleetcodeleetleetcodeleetleetcode\".\nThe 10<sup>th</sup> letter in the string is \"o\".\n</pre>\n\n<p><strong class=\"example\">Example 2:</strong></p>\n\n<pre><strong>Input:</strong> s = \"ha22\", k = 5\n<strong>Output:</strong> \"h\"\n<strong>Explanation:</strong> The decoded string is \"hahahaha\".\nThe 5<sup>th</sup> letter is \"h\".\n</pre>\n\n<p><strong class=\"example\">Example 3:</strong></p>\n\n<pre><strong>Input:</strong> s = \"a2345678999999999999999\", k = 1\n<strong>Output:</strong> \"a\"\n<strong>Explanation:</strong> The decoded string is \"a\" repeated 8301530446056247680 times.\nThe 1<sup>st</sup> letter is \"a\".\n</pre>\n\n<p>&nbsp;</p>\n<p><strong>Constraints:</strong></p>\n\n<ul>\n\t<li><code>2 &lt;= s.length &lt;= 100</code></li>\n\t<li><code>s</code> consists of lowercase English letters and digits <code>2</code> through <code>9</code>.</li>\n\t<li><code>s</code> starts with a letter.</li>\n\t<li><code>1 &lt;= k &lt;= 10<sup>9</sup></code></li>\n\t<li>It is guaranteed that <code>k</code> is less than or equal to the length of the decoded string.</li>\n\t<li>The decoded string is guaranteed to have less than <code>2<sup>63</sup></code> letters.</li>\n</ul>\n", "relatedTopics": [], "similarQuestions": [], "problemName": "decoded-string-at-index"}