{"tags": [{"duration": "1 year - 2 years", "companies": [["1 year - 2 years", "Codenation"]]}], "problem": "<p>You are given a <strong>0-indexed</strong> string <code>s</code> and are tasked with finding two <strong>non-intersecting palindromic </strong>substrings of <strong>odd</strong> length such that the product of their lengths is maximized.</p>\n\n<p>More formally, you want to choose four integers <code>i</code>, <code>j</code>, <code>k</code>, <code>l</code> such that <code>0 &lt;= i &lt;= j &lt; k &lt;= l &lt; s.length</code> and both the substrings <code>s[i...j]</code> and <code>s[k...l]</code> are palindromes and have odd lengths. <code>s[i...j]</code> denotes a substring from index <code>i</code> to index <code>j</code> <strong>inclusive</strong>.</p>\n\n<p>Return <em>the <strong>maximum</strong> possible product of the lengths of the two non-intersecting palindromic substrings.</em></p>\n\n<p>A <strong>palindrome</strong> is a string that is the same forward and backward. A <strong>substring</strong> is a contiguous sequence of characters in a string.</p>\n\n<p>&nbsp;</p>\n<p><strong class=\"example\">Example 1:</strong></p>\n\n<pre><strong>Input:</strong> s = \"ababbb\"\n<strong>Output:</strong> 9\n<strong>Explanation:</strong> Substrings \"aba\" and \"bbb\" are palindromes with odd length. product = 3 * 3 = 9.\n</pre>\n\n<p><strong class=\"example\">Example 2:</strong></p>\n\n<pre><strong>Input:</strong> s = \"zaaaxbbby\"\n<strong>Output:</strong> 9\n<strong>Explanation:</strong> Substrings \"aaa\" and \"bbb\" are palindromes with odd length. product = 3 * 3 = 9.\n</pre>\n\n<p>&nbsp;</p>\n<p><strong>Constraints:</strong></p>\n\n<ul>\n\t<li><code>2 &lt;= s.length &lt;= 10<sup>5</sup></code></li>\n\t<li><code>s</code> consists of lowercase English letters.</li>\n</ul>\n", "relatedTopics": ["String", "Rolling Hash", "Hash Function"], "similarQuestions": [{"questionName": "Maximum Product of the Length of Two Palindromic Subsequences", "difficulty": "Medium"}, {"questionName": "Minimum Cost to Make Array Equal", "difficulty": "Hard"}], "problemName": "maximum-product-of-the-length-of-two-palindromic-substrings"}