{"tags": [{"duration": "6 months - 1 year", "companies": [["6 months - 1 year", "Amazon\n6"], ["6 months - 1 year", "Google\n2"]]}, {"duration": "1 year - 2 years", "companies": [["1 year - 2 years", "Microsoft\n3"]]}], "problem": "<p>Write a program to count the number of days between two dates.</p>\n\n<p>The two dates are given as strings, their format is <code>YYYY-MM-DD</code>&nbsp;as shown in the examples.</p>\n\n<p>&nbsp;</p>\n<p><strong class=\"example\">Example 1:</strong></p>\n<pre><strong>Input:</strong> date1 = \"2019-06-29\", date2 = \"2019-06-30\"\n<strong>Output:</strong> 1\n</pre><p><strong class=\"example\">Example 2:</strong></p>\n<pre><strong>Input:</strong> date1 = \"2020-01-15\", date2 = \"2019-12-31\"\n<strong>Output:</strong> 15\n</pre>\n<p>&nbsp;</p>\n<p><strong>Constraints:</strong></p>\n\n<ul>\n\t<li>The given dates are valid&nbsp;dates between the years <code>1971</code> and <code>2100</code>.</li>\n</ul>\n", "relatedTopics": ["Math", "String"], "similarQuestions": [{"questionName": "Count Days Spent Together", "difficulty": "Easy"}], "problemName": "number-of-days-between-two-dates"}