{"tags": [{"duration": "0 - 6 months", "companies": [["0 - 6 months", "Amazon\n2"], ["0 - 6 months", "Bloomberg\n2"], ["0 - 6 months", "Visa\n2"]]}, {"duration": "6 months - 1 year", "companies": [["6 months - 1 year", "Microsoft\n5"], ["6 months - 1 year", "TikTok\n4"], ["6 months - 1 year", "Facebook\n3"], ["6 months - 1 year", "Google\n2"], ["6 months - 1 year", "Adobe\n2"], ["6 months - 1 year", "Walmart Global Tech\n2"]]}, {"duration": "1 year - 2 years", "companies": [["1 year - 2 years", "DoorDash\n4"], ["1 year - 2 years", "Apple\n3"], ["1 year - 2 years", "Oracle\n2"], ["1 year - 2 years", "Expedia\n2"], ["1 year - 2 years", "ServiceNow\n2"]]}], "problem": "<p>Given the <code>root</code> of a binary tree and an integer <code>targetSum</code>, return <em>the number of paths where the sum of the values&nbsp;along the path equals</em>&nbsp;<code>targetSum</code>.</p>\n\n<p>The path does not need to start or end at the root or a leaf, but it must go downwards (i.e., traveling only from parent nodes to child nodes).</p>\n\n<p>&nbsp;</p>\n<p><strong class=\"example\">Example 1:</strong></p>\n<img alt=\"\" src=\"https://assets.leetcode.com/uploads/2021/04/09/pathsum3-1-tree.jpg\" style=\"width: 450px; height: 386px;\">\n<pre><strong>Input:</strong> root = [10,5,-3,3,2,null,11,3,-2,null,1], targetSum = 8\n<strong>Output:</strong> 3\n<strong>Explanation:</strong> The paths that sum to 8 are shown.\n</pre>\n\n<p><strong class=\"example\">Example 2:</strong></p>\n\n<pre><strong>Input:</strong> root = [5,4,8,11,null,13,4,7,2,null,null,5,1], targetSum = 22\n<strong>Output:</strong> 3\n</pre>\n\n<p>&nbsp;</p>\n<p><strong>Constraints:</strong></p>\n\n<ul>\n\t<li>The number of nodes in the tree is in the range <code>[0, 1000]</code>.</li>\n\t<li><code>-10<sup>9</sup> &lt;= Node.val &lt;= 10<sup>9</sup></code></li>\n\t<li><code>-1000 &lt;= targetSum &lt;= 1000</code></li>\n</ul>\n", "relatedTopics": ["Tree", "Depth-First Search", "Binary Tree"], "similarQuestions": [], "problemName": "path-sum-iii"}