{"tags": [{"duration": "1 year - 2 years", "companies": [["1 year - 2 years", "Amazon"]]}], "problem": "<p>You are given a string <code>s</code> and a robot that currently holds an empty string <code>t</code>. Apply one of the following operations until <code>s</code> and <code>t</code> <strong>are both empty</strong>:</p>\n\n<ul>\n\t<li>Remove the <strong>first</strong> character of a string <code>s</code> and give it to the robot. The robot will append this character to the string <code>t</code>.</li>\n\t<li>Remove the <strong>last</strong> character of a string <code>t</code> and give it to the robot. The robot will write this character on paper.</li>\n</ul>\n\n<p>Return <em>the lexicographically smallest string that can be written on the paper.</em></p>\n\n<p>&nbsp;</p>\n<p><strong class=\"example\">Example 1:</strong></p>\n\n<pre><strong>Input:</strong> s = \"zza\"\n<strong>Output:</strong> \"azz\"\n<strong>Explanation:</strong> Let p denote the written string.\nInitially p=\"\", s=\"zza\", t=\"\".\nPerform first operation three times p=\"\", s=\"\", t=\"zza\".\nPerform second operation three times p=\"azz\", s=\"\", t=\"\".\n</pre>\n\n<p><strong class=\"example\">Example 2:</strong></p>\n\n<pre><strong>Input:</strong> s = \"bac\"\n<strong>Output:</strong> \"abc\"\n<strong>Explanation:</strong> Let p denote the written string.\nPerform first operation twice p=\"\", s=\"c\", t=\"ba\". \nPerform second operation twice p=\"ab\", s=\"c\", t=\"\". \nPerform first operation p=\"ab\", s=\"\", t=\"c\". \nPerform second operation p=\"abc\", s=\"\", t=\"\".\n</pre>\n\n<p><strong class=\"example\">Example 3:</strong></p>\n\n<pre><strong>Input:</strong> s = \"bdda\"\n<strong>Output:</strong> \"addb\"\n<strong>Explanation:</strong> Let p denote the written string.\nInitially p=\"\", s=\"bdda\", t=\"\".\nPerform first operation four times p=\"\", s=\"\", t=\"bdda\".\nPerform second operation four times p=\"addb\", s=\"\", t=\"\".\n</pre>\n\n<p>&nbsp;</p>\n<p><strong>Constraints:</strong></p>\n\n<ul>\n\t<li><code>1 &lt;= s.length &lt;= 10<sup>5</sup></code></li>\n\t<li><code>s</code> consists of only English lowercase letters.</li>\n</ul>\n", "relatedTopics": ["Hash Table", "String", "Stack", "Greedy"], "similarQuestions": [], "problemName": "using-a-robot-to-print-the-lexicographically-smallest-string"}